{
  "id": "resolution-sb-12-2025-231",
  "type": "resolution",
  "number": "2025-231",
  "title": "A RESOLUTION EXPRESSING DEEPEST SYMPATHY TO THE BEREAVED FAMILY OF COOPERATIVE UNION OF LAGUNA CHAIRMAN ANGELITO EXCONDE AND RECOGNIZING HIS EFFORTS IN COOPERATIVISM IN THE MUNICIPALITY OF LOS BANOS.",
  "session_id": "sb_12_20",
  "author_ids": ["pelegrina-miko-c"],
  "status": "active",
  "date_enacted": "2025-11-27",
  "link": "https://losbanos.gov.ph/public/storage/municipal_resolution/Resolution%20No.%202025%20-%20231_1766376576.pdf",
  "subjects": []
}
