{
  "id": "resolution_sb_12_2025-239",
  "type": "resolution",
  "number": "2025-239",
  "title": "A RESOLUTION COMMENDING AND CONGRATULATING SANGGUNIANG BARANGAY OF MAAHAS FOR BEING AWARDED AS DRUG CLEARED BARANGAY IN THE MUNICIPALITY OF LOS BANOS. , ~ , ouncilors ike C. Pelegrina Autho B. Pere: : l ” Muriel Lai LerenfMae M. Bautista, . Alborida,",
  "session_id": "sb_12_22",
  "author_ids": ["alborida-benedicto-s"],
  "status": "active",
  "date_enacted": "2025-12-01",
  "link": "https://losbanos.gov.ph/public/storage/municipal_resolution/Resolution%20No.%202025%20-%20239_1766376863.pdf",
  "subjects": []
}
